setup.py
Excel_to_PDF_invoicing_26.egg-info/PKG-INFO
Excel_to_PDF_invoicing_26.egg-info/SOURCES.txt
Excel_to_PDF_invoicing_26.egg-info/dependency_links.txt
Excel_to_PDF_invoicing_26.egg-info/requires.txt
Excel_to_PDF_invoicing_26.egg-info/top_level.txt
invoicing/__init__.py
invoicing/invoice.py